{"schema":{"valid":{"type":"Boolean"},"vendor":{"type":"String"},"timeZone":{"type":"String"},"updatedAt":{"type":"Date"},"channels":{"type":"Array"},"ACL":{"type":"ACL"},"objectId":{"type":"String"},"deviceToken":{"type":"String"},"createdAt":{"type":"Date"},"deviceType":{"type":"String"},"installationId":{"type":"String"},"badge":{"type":"Number"}},"permissions":{"create":{"*":true},"find":{"*":false},"get":{"*":true},"update":{"*":true},"delete":{"*":false},"add_fields":{"*":true}},"indexes":[{"sparse":true,"background":true,"ns":"hWhBe6tJt8AOsDR6EMhHHcDi-gzGzoHsz._Installation","name":"deviceToken_1","key":{"deviceToken":1},"unique":true,"v":1},{"sparse":true,"background":true,"ns":"hWhBe6tJt8AOsDR6EMhHHcDi-gzGzoHsz._Installation","name":"subscriptionUri_1","key":{"subscriptionUri":1},"unique":true,"v":1},{"sparse":true,"background":true,"ns":"hWhBe6tJt8AOsDR6EMhHHcDi-gzGzoHsz._Installation","name":"installationId_1","key":{"installationId":1},"unique":true,"v":1}]}