{"schema":{"salt":{"type":"String"},"email":{"type":"String"},"sessionToken":{"type":"String"},"updatedAt":{"type":"Date"},"isAdmin":{"type":"Boolean","v":2,"default":false},"ACL":{"type":"ACL"},"password":{"type":"String"},"memberIndex":{"type":"Number","v":2,"auto_increment":true,"default":20},"objectId":{"type":"String"},"groupName":{"type":"String","v":2},"username":{"type":"String"},"createdAt":{"type":"Date"},"extInfo":{"type":"String","v":2,"default":""},"emailVerified":{"type":"Boolean"},"groupIndex":{"type":"Number","v":2},"mobilePhoneNumber":{"type":"String"},"noReport":{"type":"Boolean","v":2,"default":false,"comment":"不填写日志"},"authData":{"type":"Object","user_private":true},"mobilePhoneVerified":{"type":"Boolean"}}}